{
  "word": "serendipity",
  "token_glyphed": null,
  "hyperwebster_address": null,
  "semantic": {
    "denotation": "A combination of events which have come together by chance to make a surprisingly good or wonderful outcome.",
    "connotations": [],
    "synonyms": [
      "chance",
      "luck"
    ],
    "antonyms": [
      "Murphy's law",
      "perfect storm"
    ],
    "sense_inventory": [
      {
        "pos": "noun",
        "definition": "A combination of events which have come together by chance to make a surprisingly good or wonderful outcome.",
        "example": ""
      },
      {
        "pos": "noun",
        "definition": "An unsought, unintended, and/or unexpected, but fortunate, discovery and/or learning experience that happens by accident.",
        "example": ""
      }
    ],
    "raw_wiktionary": []
  },
  "etymology": {
    "prose": "",
    "root_language": "",
    "first_attested": ""
  },
  "phonology": {
    "ipa": [
      "/ˌsɛ.ɹən.ˈdɪ.pɪ.ti/",
      "/ˌsɛ.ɹən.ˈdɪ.pɪ.ti/"
    ],
    "phonetics_raw": [
      "/ˌsɛ.ɹən.ˈdɪ.pɪ.ti/",
      "/ˌsɛ.ɹən.ˈdɪ.pɪ.ti/"
    ],
    "syllable_count": 0
  },
  "morphology": {
    "primary_pos": "noun"
  },
  "associative": {
    "synonyms_datamuse": [
      "chance",
      "accident",
      "random",
      "coincidence",
      "randomness",
      "luck",
      "godsend",
      "trouvaille",
      "kismet",
      "occasion",
      "fortuity",
      "minor miracle",
      "luck of the draw",
      "fortune",
      "fortunings",
      "god-send",
      "opportunity",
      "luck of the devil",
      "chance-medley",
      "dumb luck"
    ],
    "rhymes": [],
    "homophones": [],
    "triggers": [
      "wheedle",
      "sundae",
      "cybernetic",
      "walpole",
      "dessert",
      "guinness",
      "horace",
      "luke",
      "audition",
      "coined",
      "kate",
      "exhibition",
      "restaurant",
      "discovery",
      "dream",
      "chance",
      "pink",
      "http",
      "expensive",
      "starring"
    ],
    "left_collocates": [],
    "right_collocates": []
  },
  "encyclopedic": {
    "summary": "",
    "title": "",
    "url": "",
    "disambiguation": false
  },
  "translations": {},
  "resonance": {
    "first_encountered": "2026-05-03T11:11:41.772624+00:00",
    "learning_source": "__incomplete__:etymology",
    "confidence": 0.0
  },
  "meta": {
    "acquired_at": "2026-05-03T11:13:39.858886+00:00",
    "sources_hit": [
      "free_dictionary",
      "datamuse"
    ],
    "version": "1.0"
  }
}